my_django_tweaks/__init__.py
my_django_tweaks/autodoc.py
my_django_tweaks/autofilter.py
my_django_tweaks/logging_config.py
my_django_tweaks/mixins.py
my_django_tweaks/optimizator.py
my_django_tweaks/pagination.py
my_django_tweaks/serializers.py
my_django_tweaks/settings.py
my_django_tweaks/versioning.py
my_django_tweaks/__pycache__/__init__.cpython-37.pyc
my_django_tweaks/__pycache__/__init__.cpython-38.pyc
my_django_tweaks/__pycache__/autodoc.cpython-37.pyc
my_django_tweaks/__pycache__/autodoc.cpython-38.pyc
my_django_tweaks/__pycache__/autofilter.cpython-37.pyc
my_django_tweaks/__pycache__/autofilter.cpython-38.pyc
my_django_tweaks/__pycache__/mixins.cpython-37.pyc
my_django_tweaks/__pycache__/mixins.cpython-38.pyc
my_django_tweaks/__pycache__/optimizator.cpython-37.pyc
my_django_tweaks/__pycache__/optimizator.cpython-38.pyc
my_django_tweaks/__pycache__/pagination.cpython-37.pyc
my_django_tweaks/__pycache__/pagination.cpython-38.pyc
my_django_tweaks/__pycache__/serializers.cpython-37.pyc
my_django_tweaks/__pycache__/serializers.cpython-38.pyc
my_django_tweaks/__pycache__/settings.cpython-37.pyc
my_django_tweaks/__pycache__/settings.cpython-38.pyc
my_django_tweaks/__pycache__/versioning.cpython-37.pyc
my_django_tweaks/__pycache__/versioning.cpython-38.pyc
my_django_tweaks/test_utils/__init__.py
my_django_tweaks/test_utils/lock_limiter.py
my_django_tweaks/test_utils/query_counter.py
my_django_tweaks/test_utils/__pycache__/__init__.cpython-37.pyc
my_django_tweaks/test_utils/__pycache__/__init__.cpython-38.pyc
my_django_tweaks/test_utils/__pycache__/lock_limiter.cpython-37.pyc
my_django_tweaks/test_utils/__pycache__/lock_limiter.cpython-38.pyc
my_django_tweaks/test_utils/__pycache__/query_counter.cpython-37.pyc
my_django_tweaks/test_utils/__pycache__/query_counter.cpython-38.pyc
my_django_tweaks-0.0.6.dist-info/LICENSE
my_django_tweaks-0.0.6.dist-info/METADATA
my_django_tweaks-0.0.6.dist-info/WHEEL
my_django_tweaks-0.0.6.dist-info/top_level.txt
my_django_tweaks-0.0.6.dist-info/RECORD
