Metadata-Version: 2.1
Name: my-django-tweaks
Version: 0.0.6
Summary: A collection of various tools used to improve Django and Django Rest Framework developments
Home-page: https://github.com/ricard33/my_django_tweaks
Author: Cedric RICARD
Author-email: ricard33@gmail.com
License: MIT
Platform: UNKNOWN
Classifier: Development Status :: 4 - Beta
Classifier: Environment :: Web Environment
Classifier: Framework :: Django
Classifier: Intended Audience :: Developers
Classifier: Operating System :: OS Independent
Classifier: Programming Language :: Python
Classifier: Programming Language :: Python :: 3.6
Classifier: Topic :: Internet :: WWW/HTTP
Requires-Dist: six (>=1.10)
Requires-Dist: djangorestframework (>=3.7.0)
Requires-Dist: django-rest-swagger (>0.3.9)
Requires-Dist: django-filter (>=1.1.0)
Requires-Dist: watchdog
